transferit/__init__.py
transferit/__main__.py
transferit/callbacks.py
transferit/cli.py
transferit/exceptions.py
transferit/preparation.py
transferit/training.py
transferit/version.py
transferit/wrapping.py
transferit-0.1.0.dist-info/LICENSE
transferit-0.1.0.dist-info/METADATA
transferit-0.1.0.dist-info/WHEEL
transferit-0.1.0.dist-info/entry_points.txt
transferit-0.1.0.dist-info/top_level.txt
transferit-0.1.0.dist-info/RECORD
